{
  "cost": 59,
  "interval": "0:01:00",
  "namespace": "Microsoft.Compute/virtualMachines",
  "resourceregion": "uksouth",
  "timespan": "2022-02-20T03:30:25Z/2022-02-20T04:30:25Z",
  "value": [
    {
      "displayDescription": "The number of billable bytes received on all network interfaces by the Virtual Machine(s) (Incoming Traffic) (Deprecated)",
      "errorCode": "Success",
      "id": "/subscriptions/6a1c9c00-ef6b-4bbf-a3f1-ca2c019f31e9/resourceGroups/krishangs_resource/providers/Microsoft.Compute/virtualMachines/orange-g-site/providers/Microsoft.Insights/metrics/Network In",
      "name": {
        "localizedValue": "Network In Billable (Deprecated)",
        "value": "Network In"
      },
      "resourceGroup": "krishangs_resource",
      "timeseries": [
        {
          "data": [
            {
              "average": null,
              "count": null,
              "maximum": null,
              "minimum": null,
              "timeStamp": "2022-02-20T03:30:00+00:00",
              "total": null
            },
            {
              "average": null,
              "count": null,
              "maximum": null,
              "minimum": null,
              "timeStamp": "2022-02-20T03:31:00+00:00",
              "total": null
            },
            {
              "average": null,
              "count": null,
              "maximum": null,
              "minimum": null,
              "timeStamp": "2022-02-20T03:32:00+00:00",
              "total": null
            },
            {
              "average": null,
              "count": null,
              "maximum": null,
              "minimum": null,
              "timeStamp": "2022-02-20T03:33:00+00:00",
              "total": null
            },
            {
              "average": null,
              "count": null,
              "maximum": null,
              "minimum": null,
              "timeStamp": "2022-02-20T03:34:00+00:00",
              "total": null
            },
            {
              "average": null,
              "count": null,
              "maximum": null,
              "minimum": null,
              "timeStamp": "2022-02-20T03:35:00+00:00",
              "total": null
            },
            {
              "average": null,
              "count": null,
              "maximum": null,
              "minimum": null,
              "timeStamp": "2022-02-20T03:36:00+00:00",
              "total": null
            },
            {
              "average": null,
              "count": null,
              "maximum": null,
              "minimum": null,
              "timeStamp": "2022-02-20T03:37:00+00:00",
              "total": null
            },
            {
              "average": null,
              "count": null,
              "maximum": null,
              "minimum": null,
              "timeStamp": "2022-02-20T03:38:00+00:00",
              "total": null
            },
            {
              "average": null,
              "count": null,
              "maximum": null,
              "minimum": null,
              "timeStamp": "2022-02-20T03:39:00+00:00",
              "total": null
            },
            {
              "average": null,
              "count": null,
              "maximum": null,
              "minimum": null,
              "timeStamp": "2022-02-20T03:40:00+00:00",
              "total": null
            },
            {
              "average": null,
              "count": null,
              "maximum": null,
              "minimum": null,
              "timeStamp": "2022-02-20T03:41:00+00:00",
              "total": 0.0
            },
            {
              "average": null,
              "count": null,
              "maximum": null,
              "minimum": null,
              "timeStamp": "2022-02-20T03:42:00+00:00",
              "total": 0.0
            },
            {
              "average": null,
              "count": null,
              "maximum": null,
              "minimum": null,
              "timeStamp": "2022-02-20T03:43:00+00:00",
              "total": 0.0
            },
            {
              "average": null,
              "count": null,
              "maximum": null,
              "minimum": null,
              "timeStamp": "2022-02-20T03:44:00+00:00",
              "total": 108136482.0
            },
            {
              "average": null,
              "count": null,
              "maximum": null,
              "minimum": null,
              "timeStamp": "2022-02-20T03:45:00+00:00",
              "total": 550251446.0
            },
            {
              "average": null,
              "count": null,
              "maximum": null,
              "minimum": null,
              "timeStamp": "2022-02-20T03:46:00+00:00",
              "total": 253174012.0
            },
            {
              "average": null,
              "count": null,
              "maximum": null,
              "minimum": null,
              "timeStamp": "2022-02-20T03:47:00+00:00",
              "total": 454947561.0
            },
            {
              "average": null,
              "count": null,
              "maximum": null,
              "minimum": null,
              "timeStamp": "2022-02-20T03:48:00+00:00",
              "total": 37668.0
            },
            {
              "average": null,
              "count": null,
              "maximum": null,
              "minimum": null,
              "timeStamp": "2022-02-20T03:49:00+00:00",
              "total": 20798.0
            },
            {
              "average": null,
              "count": null,
              "maximum": null,
              "minimum": null,
              "timeStamp": "2022-02-20T03:50:00+00:00",
              "total": 1020.0
            },
            {
              "average": null,
              "count": null,
              "maximum": null,
              "minimum": null,
              "timeStamp": "2022-02-20T03:51:00+00:00",
              "total": 612.0
            },
            {
              "average": null,
              "count": null,
              "maximum": null,
              "minimum": null,
              "timeStamp": "2022-02-20T03:52:00+00:00",
              "total": 648.0
            },
            {
              "average": null,
              "count": null,
              "maximum": null,
              "minimum": null,
              "timeStamp": "2022-02-20T03:53:00+00:00",
              "total": 306.0
            },
            {
              "average": null,
              "count": null,
              "maximum": null,
              "minimum": null,
              "timeStamp": "2022-02-20T03:54:00+00:00",
              "total": 1122.0
            },
            {
              "average": null,
              "count": null,
              "maximum": null,
              "minimum": null,
              "timeStamp": "2022-02-20T03:55:00+00:00",
              "total": 44632920.0
            },
            {
              "average": null,
              "count": null,
              "maximum": null,
              "minimum": null,
              "timeStamp": "2022-02-20T03:56:00+00:00",
              "total": 96039399.0
            },
            {
              "average": null,
              "count": null,
              "maximum": null,
              "minimum": null,
              "timeStamp": "2022-02-20T03:57:00+00:00",
              "total": 97337614.0
            },
            {
              "average": null,
              "count": null,
              "maximum": null,
              "minimum": null,
              "timeStamp": "2022-02-20T03:58:00+00:00",
              "total": 97759329.0
            },
            {
              "average": null,
              "count": null,
              "maximum": null,
              "minimum": null,
              "timeStamp": "2022-02-20T03:59:00+00:00",
              "total": 98373004.0
            },
            {
              "average": null,
              "count": null,
              "maximum": null,
              "minimum": null,
              "timeStamp": "2022-02-20T04:00:00+00:00",
              "total": 97576858.0
            },
            {
              "average": null,
              "count": null,
              "maximum": null,
              "minimum": null,
              "timeStamp": "2022-02-20T04:01:00+00:00",
              "total": 98521441.0
            },
            {
              "average": null,
              "count": null,
              "maximum": null,
              "minimum": null,
              "timeStamp": "2022-02-20T04:02:00+00:00",
              "total": 97642461.0
            },
            {
              "average": null,
              "count": null,
              "maximum": null,
              "minimum": null,
              "timeStamp": "2022-02-20T04:03:00+00:00",
              "total": 97012715.0
            },
            {
              "average": null,
              "count": null,
              "maximum": null,
              "minimum": null,
              "timeStamp": "2022-02-20T04:04:00+00:00",
              "total": 97464023.0
            },
            {
              "average": null,
              "count": null,
              "maximum": null,
              "minimum": null,
              "timeStamp": "2022-02-20T04:05:00+00:00",
              "total": 97917679.0
            },
            {
              "average": null,
              "count": null,
              "maximum": null,
              "minimum": null,
              "timeStamp": "2022-02-20T04:06:00+00:00",
              "total": 98036698.0
            },
            {
              "average": null,
              "count": null,
              "maximum": null,
              "minimum": null,
              "timeStamp": "2022-02-20T04:07:00+00:00",
              "total": 97507138.0
            },
            {
              "average": null,
              "count": null,
              "maximum": null,
              "minimum": null,
              "timeStamp": "2022-02-20T04:08:00+00:00",
              "total": 96938357.0
            },
            {
              "average": null,
              "count": null,
              "maximum": null,
              "minimum": null,
              "timeStamp": "2022-02-20T04:09:00+00:00",
              "total": 97078789.0
            },
            {
              "average": null,
              "count": null,
              "maximum": null,
              "minimum": null,
              "timeStamp": "2022-02-20T04:10:00+00:00",
              "total": 97707076.0
            },
            {
              "average": null,
              "count": null,
              "maximum": null,
              "minimum": null,
              "timeStamp": "2022-02-20T04:11:00+00:00",
              "total": 97631766.0
            },
            {
              "average": null,
              "count": null,
              "maximum": null,
              "minimum": null,
              "timeStamp": "2022-02-20T04:12:00+00:00",
              "total": 97402681.0
            },
            {
              "average": null,
              "count": null,
              "maximum": null,
              "minimum": null,
              "timeStamp": "2022-02-20T04:13:00+00:00",
              "total": 98103699.0
            },
            {
              "average": null,
              "count": null,
              "maximum": null,
              "minimum": null,
              "timeStamp": "2022-02-20T04:14:00+00:00",
              "total": 97895633.0
            },
            {
              "average": null,
              "count": null,
              "maximum": null,
              "minimum": null,
              "timeStamp": "2022-02-20T04:15:00+00:00",
              "total": 97403180.0
            },
            {
              "average": null,
              "count": null,
              "maximum": null,
              "minimum": null,
              "timeStamp": "2022-02-20T04:16:00+00:00",
              "total": 97714258.0
            },
            {
              "average": null,
              "count": null,
              "maximum": null,
              "minimum": null,
              "timeStamp": "2022-02-20T04:17:00+00:00",
              "total": 96971791.0
            },
            {
              "average": null,
              "count": null,
              "maximum": null,
              "minimum": null,
              "timeStamp": "2022-02-20T04:18:00+00:00",
              "total": 98025376.0
            },
            {
              "average": null,
              "count": null,
              "maximum": null,
              "minimum": null,
              "timeStamp": "2022-02-20T04:19:00+00:00",
              "total": 97258249.0
            },
            {
              "average": null,
              "count": null,
              "maximum": null,
              "minimum": null,
              "timeStamp": "2022-02-20T04:20:00+00:00",
              "total": 97478608.0
            },
            {
              "average": null,
              "count": null,
              "maximum": null,
              "minimum": null,
              "timeStamp": "2022-02-20T04:21:00+00:00",
              "total": 97279224.0
            },
            {
              "average": null,
              "count": null,
              "maximum": null,
              "minimum": null,
              "timeStamp": "2022-02-20T04:22:00+00:00",
              "total": 97890623.0
            },
            {
              "average": null,
              "count": null,
              "maximum": null,
              "minimum": null,
              "timeStamp": "2022-02-20T04:23:00+00:00",
              "total": 97541709.0
            },
            {
              "average": null,
              "count": null,
              "maximum": null,
              "minimum": null,
              "timeStamp": "2022-02-20T04:24:00+00:00",
              "total": 97333466.0
            },
            {
              "average": null,
              "count": null,
              "maximum": null,
              "minimum": null,
              "timeStamp": "2022-02-20T04:25:00+00:00",
              "total": 50684457.0
            },
            {
              "average": null,
              "count": null,
              "maximum": null,
              "minimum": null,
              "timeStamp": "2022-02-20T04:26:00+00:00",
              "total": 670.0
            },
            {
              "average": null,
              "count": null,
              "maximum": null,
              "minimum": null,
              "timeStamp": "2022-02-20T04:27:00+00:00",
              "total": 816.0
            },
            {
              "average": null,
              "count": null,
              "maximum": null,
              "minimum": null,
              "timeStamp": "2022-02-20T04:28:00+00:00",
              "total": 1020.0
            },
            {
              "average": null,
              "count": null,
              "maximum": null,
              "minimum": null,
              "timeStamp": "2022-02-20T04:29:00+00:00",
              "total": null
            }
          ],
          "metadatavalues": []
        }
      ],
      "type": "Microsoft.Insights/metrics",
      "unit": "Bytes"
    }
  ]
}
