{
  "cost": 59,
  "interval": "0:01:00",
  "namespace": "Microsoft.Compute/virtualMachines",
  "resourceregion": "uksouth",
  "timespan": "2022-01-27T22:54:06Z/2022-01-27T23:54:06Z",
  "value": [
    {
      "displayDescription": "The percentage of allocated compute units that are currently in use by the Virtual Machine(s)",
      "errorCode": "Success",
      "id": "/subscriptions/6a1c9c00-ef6b-4bbf-a3f1-ca2c019f31e9/resourceGroups/krishangs_resource/providers/Microsoft.Compute/virtualMachines/pineapplication-f-site/providers/Microsoft.Insights/metrics/Percentage CPU",
      "name": {
        "localizedValue": "Percentage CPU",
        "value": "Percentage CPU"
      },
      "resourceGroup": "krishangs_resource",
      "timeseries": [
        {
          "data": [
            {
              "average": 5.4325,
              "count": null,
              "maximum": null,
              "minimum": null,
              "timeStamp": "2022-01-27T22:54:00+00:00",
              "total": null
            },
            {
              "average": 2.865,
              "count": null,
              "maximum": null,
              "minimum": null,
              "timeStamp": "2022-01-27T22:55:00+00:00",
              "total": null
            },
            {
              "average": 11.9875,
              "count": null,
              "maximum": null,
              "minimum": null,
              "timeStamp": "2022-01-27T22:56:00+00:00",
              "total": null
            },
            {
              "average": 8.35,
              "count": null,
              "maximum": null,
              "minimum": null,
              "timeStamp": "2022-01-27T22:57:00+00:00",
              "total": null
            },
            {
              "average": 3.1171875,
              "count": null,
              "maximum": null,
              "minimum": null,
              "timeStamp": "2022-01-27T22:58:00+00:00",
              "total": null
            },
            {
              "average": 3.84375,
              "count": null,
              "maximum": null,
              "minimum": null,
              "timeStamp": "2022-01-27T22:59:00+00:00",
              "total": null
            },
            {
              "average": 0.741875,
              "count": null,
              "maximum": null,
              "minimum": null,
              "timeStamp": "2022-01-27T23:00:00+00:00",
              "total": null
            },
            {
              "average": 0.7165625,
              "count": null,
              "maximum": null,
              "minimum": null,
              "timeStamp": "2022-01-27T23:01:00+00:00",
              "total": null
            },
            {
              "average": 0.7053125,
              "count": null,
              "maximum": null,
              "minimum": null,
              "timeStamp": "2022-01-27T23:02:00+00:00",
              "total": null
            },
            {
              "average": 0.7065625,
              "count": null,
              "maximum": null,
              "minimum": null,
              "timeStamp": "2022-01-27T23:03:00+00:00",
              "total": null
            },
            {
              "average": 0.6978125,
              "count": null,
              "maximum": null,
              "minimum": null,
              "timeStamp": "2022-01-27T23:04:00+00:00",
              "total": null
            },
            {
              "average": 0.715,
              "count": null,
              "maximum": null,
              "minimum": null,
              "timeStamp": "2022-01-27T23:05:00+00:00",
              "total": null
            },
            {
              "average": 0.7109375,
              "count": null,
              "maximum": null,
              "minimum": null,
              "timeStamp": "2022-01-27T23:06:00+00:00",
              "total": null
            },
            {
              "average": 0.7190625,
              "count": null,
              "maximum": null,
              "minimum": null,
              "timeStamp": "2022-01-27T23:07:00+00:00",
              "total": null
            },
            {
              "average": 0.6921875,
              "count": null,
              "maximum": null,
              "minimum": null,
              "timeStamp": "2022-01-27T23:08:00+00:00",
              "total": null
            },
            {
              "average": 0.6415625,
              "count": null,
              "maximum": null,
              "minimum": null,
              "timeStamp": "2022-01-27T23:09:00+00:00",
              "total": null
            },
            {
              "average": 0.67375,
              "count": null,
              "maximum": null,
              "minimum": null,
              "timeStamp": "2022-01-27T23:10:00+00:00",
              "total": null
            },
            {
              "average": 0.6603125,
              "count": null,
              "maximum": null,
              "minimum": null,
              "timeStamp": "2022-01-27T23:11:00+00:00",
              "total": null
            },
            {
              "average": 0.6775,
              "count": null,
              "maximum": null,
              "minimum": null,
              "timeStamp": "2022-01-27T23:12:00+00:00",
              "total": null
            },
            {
              "average": 0.6859375,
              "count": null,
              "maximum": null,
              "minimum": null,
              "timeStamp": "2022-01-27T23:13:00+00:00",
              "total": null
            },
            {
              "average": 0.68625,
              "count": null,
              "maximum": null,
              "minimum": null,
              "timeStamp": "2022-01-27T23:14:00+00:00",
              "total": null
            },
            {
              "average": 0.685625,
              "count": null,
              "maximum": null,
              "minimum": null,
              "timeStamp": "2022-01-27T23:15:00+00:00",
              "total": null
            },
            {
              "average": 11.7721875,
              "count": null,
              "maximum": null,
              "minimum": null,
              "timeStamp": "2022-01-27T23:16:00+00:00",
              "total": null
            },
            {
              "average": 11.1671875,
              "count": null,
              "maximum": null,
              "minimum": null,
              "timeStamp": "2022-01-27T23:17:00+00:00",
              "total": null
            },
            {
              "average": 1.853125,
              "count": null,
              "maximum": null,
              "minimum": null,
              "timeStamp": "2022-01-27T23:18:00+00:00",
              "total": null
            },
            {
              "average": 3.580625,
              "count": null,
              "maximum": null,
              "minimum": null,
              "timeStamp": "2022-01-27T23:19:00+00:00",
              "total": null
            },
            {
              "average": 1.2934375,
              "count": null,
              "maximum": null,
              "minimum": null,
              "timeStamp": "2022-01-27T23:20:00+00:00",
              "total": null
            },
            {
              "average": 2.2384375,
              "count": null,
              "maximum": null,
              "minimum": null,
              "timeStamp": "2022-01-27T23:21:00+00:00",
              "total": null
            },
            {
              "average": 1.79125,
              "count": null,
              "maximum": null,
              "minimum": null,
              "timeStamp": "2022-01-27T23:22:00+00:00",
              "total": null
            },
            {
              "average": 2.831875,
              "count": null,
              "maximum": null,
              "minimum": null,
              "timeStamp": "2022-01-27T23:23:00+00:00",
              "total": null
            },
            {
              "average": 2.1021875,
              "count": null,
              "maximum": null,
              "minimum": null,
              "timeStamp": "2022-01-27T23:24:00+00:00",
              "total": null
            },
            {
              "average": 2.604375,
              "count": null,
              "maximum": null,
              "minimum": null,
              "timeStamp": "2022-01-27T23:25:00+00:00",
              "total": null
            },
            {
              "average": 1.2875,
              "count": null,
              "maximum": null,
              "minimum": null,
              "timeStamp": "2022-01-27T23:26:00+00:00",
              "total": null
            },
            {
              "average": 2.2603125,
              "count": null,
              "maximum": null,
              "minimum": null,
              "timeStamp": "2022-01-27T23:27:00+00:00",
              "total": null
            },
            {
              "average": 1.959375,
              "count": null,
              "maximum": null,
              "minimum": null,
              "timeStamp": "2022-01-27T23:28:00+00:00",
              "total": null
            },
            {
              "average": 1.1403125,
              "count": null,
              "maximum": null,
              "minimum": null,
              "timeStamp": "2022-01-27T23:29:00+00:00",
              "total": null
            },
            {
              "average": 3.22875,
              "count": null,
              "maximum": null,
              "minimum": null,
              "timeStamp": "2022-01-27T23:30:00+00:00",
              "total": null
            },
            {
              "average": 0.871875,
              "count": null,
              "maximum": null,
              "minimum": null,
              "timeStamp": "2022-01-27T23:31:00+00:00",
              "total": null
            },
            {
              "average": 2.06875,
              "count": null,
              "maximum": null,
              "minimum": null,
              "timeStamp": "2022-01-27T23:32:00+00:00",
              "total": null
            },
            {
              "average": 2.8690625,
              "count": null,
              "maximum": null,
              "minimum": null,
              "timeStamp": "2022-01-27T23:33:00+00:00",
              "total": null
            },
            {
              "average": 1.23,
              "count": null,
              "maximum": null,
              "minimum": null,
              "timeStamp": "2022-01-27T23:34:00+00:00",
              "total": null
            },
            {
              "average": 0.7290625,
              "count": null,
              "maximum": null,
              "minimum": null,
              "timeStamp": "2022-01-27T23:35:00+00:00",
              "total": null
            },
            {
              "average": 2.4459375,
              "count": null,
              "maximum": null,
              "minimum": null,
              "timeStamp": "2022-01-27T23:36:00+00:00",
              "total": null
            },
            {
              "average": 1.3434375,
              "count": null,
              "maximum": null,
              "minimum": null,
              "timeStamp": "2022-01-27T23:37:00+00:00",
              "total": null
            },
            {
              "average": 1.64125,
              "count": null,
              "maximum": null,
              "minimum": null,
              "timeStamp": "2022-01-27T23:38:00+00:00",
              "total": null
            },
            {
              "average": 1.17,
              "count": null,
              "maximum": null,
              "minimum": null,
              "timeStamp": "2022-01-27T23:39:00+00:00",
              "total": null
            },
            {
              "average": 0.7609375,
              "count": null,
              "maximum": null,
              "minimum": null,
              "timeStamp": "2022-01-27T23:40:00+00:00",
              "total": null
            },
            {
              "average": 1.2346875,
              "count": null,
              "maximum": null,
              "minimum": null,
              "timeStamp": "2022-01-27T23:41:00+00:00",
              "total": null
            },
            {
              "average": 2.27125,
              "count": null,
              "maximum": null,
              "minimum": null,
              "timeStamp": "2022-01-27T23:42:00+00:00",
              "total": null
            },
            {
              "average": 0.8578125,
              "count": null,
              "maximum": null,
              "minimum": null,
              "timeStamp": "2022-01-27T23:43:00+00:00",
              "total": null
            },
            {
              "average": 1.446875,
              "count": null,
              "maximum": null,
              "minimum": null,
              "timeStamp": "2022-01-27T23:44:00+00:00",
              "total": null
            },
            {
              "average": 1.5953125,
              "count": null,
              "maximum": null,
              "minimum": null,
              "timeStamp": "2022-01-27T23:45:00+00:00",
              "total": null
            },
            {
              "average": 0.7725,
              "count": null,
              "maximum": null,
              "minimum": null,
              "timeStamp": "2022-01-27T23:46:00+00:00",
              "total": null
            },
            {
              "average": 0.699375,
              "count": null,
              "maximum": null,
              "minimum": null,
              "timeStamp": "2022-01-27T23:47:00+00:00",
              "total": null
            },
            {
              "average": 0.6790625,
              "count": null,
              "maximum": null,
              "minimum": null,
              "timeStamp": "2022-01-27T23:48:00+00:00",
              "total": null
            },
            {
              "average": 0.68875,
              "count": null,
              "maximum": null,
              "minimum": null,
              "timeStamp": "2022-01-27T23:49:00+00:00",
              "total": null
            },
            {
              "average": 0.7075,
              "count": null,
              "maximum": null,
              "minimum": null,
              "timeStamp": "2022-01-27T23:50:00+00:00",
              "total": null
            },
            {
              "average": 0.7025,
              "count": null,
              "maximum": null,
              "minimum": null,
              "timeStamp": "2022-01-27T23:51:00+00:00",
              "total": null
            },
            {
              "average": 0.644375,
              "count": null,
              "maximum": null,
              "minimum": null,
              "timeStamp": "2022-01-27T23:52:00+00:00",
              "total": null
            },
            {
              "average": null,
              "count": null,
              "maximum": null,
              "minimum": null,
              "timeStamp": "2022-01-27T23:53:00+00:00",
              "total": null
            }
          ],
          "metadatavalues": []
        }
      ],
      "type": "Microsoft.Insights/metrics",
      "unit": "Percent"
    }
  ]
}
