{
  "cost": 59,
  "interval": "0:01:00",
  "namespace": "Microsoft.Compute/virtualMachines",
  "resourceregion": "uksouth",
  "timespan": "2022-01-27T19:05:37Z/2022-01-27T20:05:37Z",
  "value": [
    {
      "displayDescription": "The number of billable bytes received on all network interfaces by the Virtual Machine(s) (Incoming Traffic) (Deprecated)",
      "errorCode": "Success",
      "id": "/subscriptions/6a1c9c00-ef6b-4bbf-a3f1-ca2c019f31e9/resourceGroups/krishangs_resource/providers/Microsoft.Compute/virtualMachines/pineapplication-b-site/providers/Microsoft.Insights/metrics/Network In",
      "name": {
        "localizedValue": "Network In Billable (Deprecated)",
        "value": "Network In"
      },
      "resourceGroup": "krishangs_resource",
      "timeseries": [
        {
          "data": [
            {
              "average": null,
              "count": null,
              "maximum": null,
              "minimum": null,
              "timeStamp": "2022-01-27T19:05:00+00:00",
              "total": 485350996.0
            },
            {
              "average": null,
              "count": null,
              "maximum": null,
              "minimum": null,
              "timeStamp": "2022-01-27T19:06:00+00:00",
              "total": 8783121.0
            },
            {
              "average": null,
              "count": null,
              "maximum": null,
              "minimum": null,
              "timeStamp": "2022-01-27T19:07:00+00:00",
              "total": 10266021.0
            },
            {
              "average": null,
              "count": null,
              "maximum": null,
              "minimum": null,
              "timeStamp": "2022-01-27T19:08:00+00:00",
              "total": 11600678.0
            },
            {
              "average": null,
              "count": null,
              "maximum": null,
              "minimum": null,
              "timeStamp": "2022-01-27T19:09:00+00:00",
              "total": 229048658.0
            },
            {
              "average": null,
              "count": null,
              "maximum": null,
              "minimum": null,
              "timeStamp": "2022-01-27T19:10:00+00:00",
              "total": 75014523.0
            },
            {
              "average": null,
              "count": null,
              "maximum": null,
              "minimum": null,
              "timeStamp": "2022-01-27T19:11:00+00:00",
              "total": 59345481.0
            },
            {
              "average": null,
              "count": null,
              "maximum": null,
              "minimum": null,
              "timeStamp": "2022-01-27T19:12:00+00:00",
              "total": 283577517.0
            },
            {
              "average": null,
              "count": null,
              "maximum": null,
              "minimum": null,
              "timeStamp": "2022-01-27T19:13:00+00:00",
              "total": 178831666.0
            },
            {
              "average": null,
              "count": null,
              "maximum": null,
              "minimum": null,
              "timeStamp": "2022-01-27T19:14:00+00:00",
              "total": 9847045.0
            },
            {
              "average": null,
              "count": null,
              "maximum": null,
              "minimum": null,
              "timeStamp": "2022-01-27T19:15:00+00:00",
              "total": 71830697.0
            },
            {
              "average": null,
              "count": null,
              "maximum": null,
              "minimum": null,
              "timeStamp": "2022-01-27T19:16:00+00:00",
              "total": 2520522.0
            },
            {
              "average": null,
              "count": null,
              "maximum": null,
              "minimum": null,
              "timeStamp": "2022-01-27T19:17:00+00:00",
              "total": 238662317.0
            },
            {
              "average": null,
              "count": null,
              "maximum": null,
              "minimum": null,
              "timeStamp": "2022-01-27T19:18:00+00:00",
              "total": 4359869.0
            },
            {
              "average": null,
              "count": null,
              "maximum": null,
              "minimum": null,
              "timeStamp": "2022-01-27T19:19:00+00:00",
              "total": 237000262.0
            },
            {
              "average": null,
              "count": null,
              "maximum": null,
              "minimum": null,
              "timeStamp": "2022-01-27T19:20:00+00:00",
              "total": 61192103.0
            },
            {
              "average": null,
              "count": null,
              "maximum": null,
              "minimum": null,
              "timeStamp": "2022-01-27T19:21:00+00:00",
              "total": 2066.0
            },
            {
              "average": null,
              "count": null,
              "maximum": null,
              "minimum": null,
              "timeStamp": "2022-01-27T19:22:00+00:00",
              "total": 1428.0
            },
            {
              "average": null,
              "count": null,
              "maximum": null,
              "minimum": null,
              "timeStamp": "2022-01-27T19:23:00+00:00",
              "total": 1428.0
            },
            {
              "average": null,
              "count": null,
              "maximum": null,
              "minimum": null,
              "timeStamp": "2022-01-27T19:24:00+00:00",
              "total": 1964.0
            },
            {
              "average": null,
              "count": null,
              "maximum": null,
              "minimum": null,
              "timeStamp": "2022-01-27T19:25:00+00:00",
              "total": 1020.0
            },
            {
              "average": null,
              "count": null,
              "maximum": null,
              "minimum": null,
              "timeStamp": "2022-01-27T19:26:00+00:00",
              "total": 1428.0
            },
            {
              "average": null,
              "count": null,
              "maximum": null,
              "minimum": null,
              "timeStamp": "2022-01-27T19:27:00+00:00",
              "total": 1326.0
            },
            {
              "average": null,
              "count": null,
              "maximum": null,
              "minimum": null,
              "timeStamp": "2022-01-27T19:28:00+00:00",
              "total": 54746.0
            },
            {
              "average": null,
              "count": null,
              "maximum": null,
              "minimum": null,
              "timeStamp": "2022-01-27T19:29:00+00:00",
              "total": 3515492.0
            },
            {
              "average": null,
              "count": null,
              "maximum": null,
              "minimum": null,
              "timeStamp": "2022-01-27T19:30:00+00:00",
              "total": 647955.0
            },
            {
              "average": null,
              "count": null,
              "maximum": null,
              "minimum": null,
              "timeStamp": "2022-01-27T19:31:00+00:00",
              "total": 67214.0
            },
            {
              "average": null,
              "count": null,
              "maximum": null,
              "minimum": null,
              "timeStamp": "2022-01-27T19:32:00+00:00",
              "total": 18720.0
            },
            {
              "average": null,
              "count": null,
              "maximum": null,
              "minimum": null,
              "timeStamp": "2022-01-27T19:33:00+00:00",
              "total": 836.0
            },
            {
              "average": null,
              "count": null,
              "maximum": null,
              "minimum": null,
              "timeStamp": "2022-01-27T19:34:00+00:00",
              "total": 1734.0
            },
            {
              "average": null,
              "count": null,
              "maximum": null,
              "minimum": null,
              "timeStamp": "2022-01-27T19:35:00+00:00",
              "total": 930.0
            },
            {
              "average": null,
              "count": null,
              "maximum": null,
              "minimum": null,
              "timeStamp": "2022-01-27T19:36:00+00:00",
              "total": 1542.0
            },
            {
              "average": null,
              "count": null,
              "maximum": null,
              "minimum": null,
              "timeStamp": "2022-01-27T19:37:00+00:00",
              "total": 1609.0
            },
            {
              "average": null,
              "count": null,
              "maximum": null,
              "minimum": null,
              "timeStamp": "2022-01-27T19:38:00+00:00",
              "total": 1836.0
            },
            {
              "average": null,
              "count": null,
              "maximum": null,
              "minimum": null,
              "timeStamp": "2022-01-27T19:39:00+00:00",
              "total": 1648818.0
            },
            {
              "average": null,
              "count": null,
              "maximum": null,
              "minimum": null,
              "timeStamp": "2022-01-27T19:40:00+00:00",
              "total": 680087.0
            },
            {
              "average": null,
              "count": null,
              "maximum": null,
              "minimum": null,
              "timeStamp": "2022-01-27T19:41:00+00:00",
              "total": 678463.0
            },
            {
              "average": null,
              "count": null,
              "maximum": null,
              "minimum": null,
              "timeStamp": "2022-01-27T19:42:00+00:00",
              "total": 361841.0
            },
            {
              "average": null,
              "count": null,
              "maximum": null,
              "minimum": null,
              "timeStamp": "2022-01-27T19:43:00+00:00",
              "total": 238541.0
            },
            {
              "average": null,
              "count": null,
              "maximum": null,
              "minimum": null,
              "timeStamp": "2022-01-27T19:44:00+00:00",
              "total": 249155.0
            },
            {
              "average": null,
              "count": null,
              "maximum": null,
              "minimum": null,
              "timeStamp": "2022-01-27T19:45:00+00:00",
              "total": 296368.0
            },
            {
              "average": null,
              "count": null,
              "maximum": null,
              "minimum": null,
              "timeStamp": "2022-01-27T19:46:00+00:00",
              "total": 396820.0
            },
            {
              "average": null,
              "count": null,
              "maximum": null,
              "minimum": null,
              "timeStamp": "2022-01-27T19:47:00+00:00",
              "total": 557093.0
            },
            {
              "average": null,
              "count": null,
              "maximum": null,
              "minimum": null,
              "timeStamp": "2022-01-27T19:48:00+00:00",
              "total": 196422.0
            },
            {
              "average": null,
              "count": null,
              "maximum": null,
              "minimum": null,
              "timeStamp": "2022-01-27T19:49:00+00:00",
              "total": 491047.0
            },
            {
              "average": null,
              "count": null,
              "maximum": null,
              "minimum": null,
              "timeStamp": "2022-01-27T19:50:00+00:00",
              "total": 230222.0
            },
            {
              "average": null,
              "count": null,
              "maximum": null,
              "minimum": null,
              "timeStamp": "2022-01-27T19:51:00+00:00",
              "total": 1571429.0
            },
            {
              "average": null,
              "count": null,
              "maximum": null,
              "minimum": null,
              "timeStamp": "2022-01-27T19:52:00+00:00",
              "total": 762614.0
            },
            {
              "average": null,
              "count": null,
              "maximum": null,
              "minimum": null,
              "timeStamp": "2022-01-27T19:53:00+00:00",
              "total": 820604.0
            },
            {
              "average": null,
              "count": null,
              "maximum": null,
              "minimum": null,
              "timeStamp": "2022-01-27T19:54:00+00:00",
              "total": 608396.0
            },
            {
              "average": null,
              "count": null,
              "maximum": null,
              "minimum": null,
              "timeStamp": "2022-01-27T19:55:00+00:00",
              "total": 147204.0
            },
            {
              "average": null,
              "count": null,
              "maximum": null,
              "minimum": null,
              "timeStamp": "2022-01-27T19:56:00+00:00",
              "total": 273479.0
            },
            {
              "average": null,
              "count": null,
              "maximum": null,
              "minimum": null,
              "timeStamp": "2022-01-27T19:57:00+00:00",
              "total": 951969.0
            },
            {
              "average": null,
              "count": null,
              "maximum": null,
              "minimum": null,
              "timeStamp": "2022-01-27T19:58:00+00:00",
              "total": 726091.0
            },
            {
              "average": null,
              "count": null,
              "maximum": null,
              "minimum": null,
              "timeStamp": "2022-01-27T19:59:00+00:00",
              "total": 632716.0
            },
            {
              "average": null,
              "count": null,
              "maximum": null,
              "minimum": null,
              "timeStamp": "2022-01-27T20:00:00+00:00",
              "total": 1775.0
            },
            {
              "average": null,
              "count": null,
              "maximum": null,
              "minimum": null,
              "timeStamp": "2022-01-27T20:01:00+00:00",
              "total": 14863.0
            },
            {
              "average": null,
              "count": null,
              "maximum": null,
              "minimum": null,
              "timeStamp": "2022-01-27T20:02:00+00:00",
              "total": 714.0
            },
            {
              "average": null,
              "count": null,
              "maximum": null,
              "minimum": null,
              "timeStamp": "2022-01-27T20:03:00+00:00",
              "total": 1122.0
            },
            {
              "average": null,
              "count": null,
              "maximum": null,
              "minimum": null,
              "timeStamp": "2022-01-27T20:04:00+00:00",
              "total": null
            }
          ],
          "metadatavalues": []
        }
      ],
      "type": "Microsoft.Insights/metrics",
      "unit": "Bytes"
    }
  ]
}
